smtk_draco.cpython-312-x86_64-linux-musl.so
smtk_draco.libs/libgcc_s-0cd532bd.so.1
smtk_draco.libs/libstdc++-5d72f927.so.6.0.33
smtk_draco-1.0.1.dist-info/METADATA
smtk_draco-1.0.1.dist-info/WHEEL
smtk_draco-1.0.1.dist-info/RECORD
smtk_draco-1.0.1.dist-info/licenses/LICENSE
