Metadata-Version: 2.2
Name: smtk_draco
Version: 1.0.1
Summary: Python wrapper of Blenders Draco bridging library
Keywords: draco,mesh compression,gltf,glb
Author: barasimumatik
Maintainer: Simumatik
License: Apache License Version 2.0 (see LICENSE)
Classifier: Intended Audience :: Developers
Classifier: Development Status :: 3 - Alpha
Classifier: License :: OSI Approved :: Apache Software License
Classifier: Programming Language :: Python :: 3
Project-URL: Repository, https://github.com/Simumatik/smtk_draco
Project-URL: Issues, https://github.com/Simumatik/smtk_draco/issues
Requires-Python: >=3.8
